ashtree/__init__.py
ashtree/baseapp.py
ashtree/command.py
ashtree/config.py
ashtree/errors.py
ashtree/middleware.py
ashtree/pagination.py
ashtree/permissions.py
ashtree/util.py
ashtree/commands/__init__.py
ashtree/commands/init.py
ashtree/project/__init__.py
ashtree/project/models.py
ashtree/project/util.py
ashtree/project/templates/controller.py.tmpl
ashtree/project/templates/model.py.tmpl
ashtree/templates/.shellrc.py
ashtree/templates/admin.py
ashtree/templates/application.toml.tmpl
ashtree/templates/app/__init__.py
ashtree/templates/app/application.py
ashtree/templates/app/auth.py
ashtree/templates/app/config.py
ashtree/templates/app/context.py
ashtree/templates/app/middleware.py
ashtree/templates/app/commands/__init__.py
ashtree/templates/app/commands/index.py
ashtree/templates/app/commands/new.py
ashtree/templates/app/commands/run.py
ashtree/templates/app/commands/shell.py
ashtree/templates/app/controllers/__init__.py
ashtree/templates/app/controllers/api/__init__.py
ashtree/templates/app/controllers/api/v1/__init__.py
ashtree/templates/app/controllers/api/v1/account.py
ashtree/templates/app/models/__init__.py
ashtree/templates/app/models/role.py
ashtree/templates/app/models/session.py
ashtree/templates/app/models/user.py
ashtree/tests/__init__.py
ashtree/tests/test_config.py
ashtree/tests/test_project.py
pyashtree-0.99.25.dist-info/METADATA
pyashtree-0.99.25.dist-info/WHEEL
pyashtree-0.99.25.dist-info/entry_points.txt
pyashtree-0.99.25.dist-info/top_level.txt
pyashtree-0.99.25.dist-info/RECORD
