Metadata-Version: 2.1
Name: pyashtree
Version: 0.99.25
Summary: a micro webframework based on fastapi and motor
Author-email: Pavel Vorobyev <aquavitale@yandex.ru>
License: MIT
Project-URL: Source, https://github.com/viert/ashtree
Keywords: fastapi,pymongo,mongodb,motor,asyncio
Requires-Python: >=3.11
Requires-Dist: fastapi[all]
Requires-Dist: pydantic
Requires-Dist: starlette
Requires-Dist: ipython
Requires-Dist: uvicorn
Requires-Dist: jinja2
Requires-Dist: mongey
Requires-Dist: bcrypt
Requires-Dist: rq
Requires-Dist: redis
